iplocationchanger/__init__.py
iplocationchanger/__main__.py
iplocationchanger/exception/iplocationchanger_exception.py
iplocationchanger/exception/location_changer_service_exception.py
iplocationchanger/exception/openvpn_service_exception.py
iplocationchanger/exception/whatismyip_service_exception.py
iplocationchanger/model/__init__.py
iplocationchanger/model/openvpn_credentials.py
iplocationchanger/service/__init__.py
iplocationchanger/service/location_changer_service.py
iplocationchanger/service/openvpn_service.py
iplocationchanger/service/whatismyip_service.py
iplocationchanger/utils/__init__.py
iplocationchanger/utils/utils.py
iplocationchanger-0.1.0.dist-info/LICENSE
iplocationchanger-0.1.0.dist-info/METADATA
iplocationchanger-0.1.0.dist-info/WHEEL
iplocationchanger-0.1.0.dist-info/top_level.txt
iplocationchanger-0.1.0.dist-info/RECORD
