Metadata-Version: 2.1
Name: iplocationchanger
Version: 0.1.0
Summary: Reliable IP location changer using OpenVPN and WhatIsMyIP
Author-email: Faizudeen Kajogbola <faizudeen@codecreek.cc>
License: MIT License
Project-URL: Homepage, https://github.com/Faaizz/iplocationchanger_python
Keywords: ip,vpn,openvpn
Classifier: License :: OSI Approved :: MIT License
Classifier: Programming Language :: Python
Classifier: Programming Language :: Python :: 3
Classifier: Operating System :: POSIX :: Linux
Classifier: Operating System :: MacOS
Requires-Python: >=3.9
License-File: LICENSE
Requires-Dist: requests (==2.28.2)
Provides-Extra: dev
Requires-Dist: coverage (==7.2.1) ; extra == 'dev'
